djangorestframework_jwt_refresh_token-0.5.dist-info/RECORD
djangorestframework_jwt_refresh_token-0.5.dist-info/DESCRIPTION.rst
djangorestframework_jwt_refresh_token-0.5.dist-info/METADATA
djangorestframework_jwt_refresh_token-0.5.dist-info/top_level.txt
djangorestframework_jwt_refresh_token-0.5.dist-info/metadata.json
djangorestframework_jwt_refresh_token-0.5.dist-info/WHEEL
refreshtoken/serializers.py
refreshtoken/models.py
refreshtoken/__init__.py
refreshtoken/views.py
refreshtoken/routers.py
refreshtoken/permissions.py
refreshtoken/__pycache__/serializers.cpython-34.pyc
refreshtoken/__pycache__/serializers.cpython-35.pyc
refreshtoken/__pycache__/models.cpython-34.pyc
refreshtoken/__pycache__/authentication.cpython-34.pyc
refreshtoken/__pycache__/views.cpython-35.pyc
refreshtoken/__pycache__/__init__.cpython-34.pyc
refreshtoken/__pycache__/permissions.cpython-34.pyc
refreshtoken/__pycache__/__init__.cpython-35.pyc
refreshtoken/__pycache__/views.cpython-34.pyc
refreshtoken/__pycache__/models.cpython-35.pyc
refreshtoken/migrations/0001_initial.py
refreshtoken/migrations/__init__.py
refreshtoken/migrations/__pycache__/0001_initial.cpython-34.pyc
refreshtoken/migrations/__pycache__/__init__.cpython-34.pyc
refreshtoken/migrations/__pycache__/0001_initial.cpython-35.pyc
refreshtoken/migrations/__pycache__/__init__.cpython-35.pyc
