Metadata-Version: 2.0
Name: djangorestframework-jwt-refresh-token
Version: 0.5
Summary: Long Refresh Tokens for JSON Web Token based authentication
Home-page: https://github.com/lock8/django-rest-framework-jwt-refresh-token
Author: Nicolas Delaby
Author-email: nicolas@noa.one
License: MIT
Platform: UNKNOWN
Classifier: Development Status :: 4 - Beta
Classifier: Environment :: Web Environment
Classifier: Framework :: Django
Classifier: Framework :: Django :: 1.11
Classifier: Framework :: Django :: 2.0
Classifier: Intended Audience :: Developers
Classifier: License :: OSI Approved :: MIT License
Classifier: Operating System :: OS Independent
Classifier: Programming Language :: Python
Classifier: Programming Language :: Python :: 3.4
Classifier: Programming Language :: Python :: 3.5
Classifier: Programming Language :: Python :: 3.6
Classifier: Topic :: Internet :: WWW/HTTP
